fasthtml_sessionnormalizer/__init__.py
fasthtml_sessionnormalizer/middleware.py
fasthtml_sessionnormalizer-0.1.0.dist-info/LICENSE
fasthtml_sessionnormalizer-0.1.0.dist-info/METADATA
fasthtml_sessionnormalizer-0.1.0.dist-info/WHEEL
fasthtml_sessionnormalizer-0.1.0.dist-info/RECORD
