Metadata-Version: 2.1
Name: fasthtml-sessionnormalizer
Version: 0.1.0
Summary: A normalizer for session middleware in FastHTML
Home-page: https://github.com/palomino79/session_normalizer_middleware
License: Apache 2.0
Author: Vince McCrae
Requires-Python: >=3.6,<4.0
Classifier: License :: Other/Proprietary License
Classifier: Programming Language :: Python :: 3
Classifier: Programming Language :: Python :: 3.6
Classifier: Programming Language :: Python :: 3.7
Classifier: Programming Language :: Python :: 3.8
Classifier: Programming Language :: Python :: 3.9
Classifier: Programming Language :: Python :: 3.10
Classifier: Programming Language :: Python :: 3.11
Classifier: Programming Language :: Python :: 3.12
Requires-Dist: python-fasthtml (>=0.4.0,<0.5.0)
